cmtool/__init__.py
cmtool/comments.py
cmtool/comments_miner.py
cmtool/environment.py
cmtool/exception_monitoring.py
cmtool/helper.py
cmtool/java_ast_parsing.py
cmtool/java_proj_miner.py
cmtool/java_project_meta_attributes.py
cmtool/json_serialization.py
cmtool/parse_source_files.py
cmtool/performance_time.py
cmtool/process_parameters.py
cmtool/proj_comments_comprehensive_attr.py
cmtool/proj_comments_main_attr.py
cmtool/project_attributes.py
cmtool/project_meta.py
cmtool/soccminer_logger.py
cmtool/source_code_details.py
cmtool/srcml.py
cmtool-0.0.4a1.data/scripts/main.py
cmtool-0.0.4a1.dist-info/LICENSE
cmtool-0.0.4a1.dist-info/METADATA
cmtool-0.0.4a1.dist-info/WHEEL
cmtool-0.0.4a1.dist-info/top_level.txt
cmtool-0.0.4a1.dist-info/RECORD
