Metadata-Version: 2.1
Name: cmtool
Version: 0.0.4a1
Summary: Miner Tool
Author: da_enthusiast
Author-email: dataapproximation.enthusiast@gmail.com
License: MIT
Platform: Linux
Classifier: Development Status :: 3 - Alpha
Classifier: License :: OSI Approved :: MIT License
Classifier: Programming Language :: Python :: 3.6
Classifier: Topic :: Text Processing :: Linguistic
License-File: LICENSE
Requires-Dist: lxml
Requires-Dist: numpy
Requires-Dist: python-dateutil
Requires-Dist: six
Requires-Dist: pytz
Requires-Dist: requests
Requires-Dist: certifi
Requires-Dist: charset-normalizer
Requires-Dist: idna
Requires-Dist: urllib3
Requires-Dist: ujson
